authentication/__init__.py
authentication/app.py
authentication/config.py
authentication/redis_config.py
authentication/auth/__init__.py
authentication/auth/crypting.py
authentication/auth/models.py
authentication/models/__init__.py
authentication/models/basemodel.py
authentication/models/db.py
authentication/models/exceptions.py
authentication/templates/login.html
authentication/templates/login_form.html
authentication/templates/logout.html
authentication/templates/logout_form.html
authentication/templates/registration.html
authentication/templates/registration_form.html
authentication/templates/update_user.html
authentication/templates/update_user_form.html
authentication/tests/__init__.py
authentication/tests/test_CRUD.py
authentication/views/__init__.py
authentication/views/wtforms.py
authentication-1.1.0.dist-info/LICENSE.txt
authentication-1.1.0.dist-info/METADATA
authentication-1.1.0.dist-info/WHEEL
authentication-1.1.0.dist-info/top_level.txt
authentication-1.1.0.dist-info/RECORD
