Metadata-Version: 2.1
Name: authentication
Version: 1.1.0
Summary: Learning authentication
Home-page: UNKNOWN
Author: Kateryna Melnykova
Author-email: forkatemelnikova@gmail.com
License: MIT
Platform: UNKNOWN
